mozprocess/__init__.py
mozprocess/mozprocess.py
mozprocess/processhandler.py
mozprocess/qijo.py
mozprocess/winprocess.py
mozprocess-1.4.0.dist-info/METADATA
mozprocess-1.4.0.dist-info/WHEEL
mozprocess-1.4.0.dist-info/top_level.txt
mozprocess-1.4.0.dist-info/RECORD
